{"settings_rates.md":"31740f21","intro_videorx.md":"794c4556","shop_shops.md":"f2a8d2ed","intro_power.md":"3fbaebfb","shop_airplanes.md":"996caa38","shop_kit.md":"84e1f29e","community_usefull.md":"be80f5b1","settings_frsky.md":"c14e851f","shop_buyveloci.md":"adcdfc59","intro_sim.md":"74db5010","community_coating.md":"1043f6bd","community_chats.md":"7372effe","community_bags.md":"491317ab","community_glossarium.md":"6c253578","intro_flightstyles.md":"880d88f7","community_software.md":"4cf69e4a","index.md":"370107f1","community_soldering.md":"33bbca64","intro_tx.md":"c08d991f","shop_nessesary.md":"bfb1ba39","intro_beginning.md":"4fbd5d1c","settings_presets.md":"ffbf507b","shop_diy.md":"6a1df22f","shop_lifehacks.md":"e4c320f5"}
